{
  "portfolios": [
    {
      "name": "calendar 2020",
      "thumnail": "/assets/img/img_2007.jpg",
      "galleryImages": [
        "/assets/img/chicken2.jpg",
        "/assets/img/dalar.jpg",
        "/assets/img/found_the_love2.jpg",
        "/assets/img/img_1627.jpg",
        "/assets/img/img_1683.jpg",
        "/assets/img/img_1994.png",
        "/assets/img/img_1995.png",
        "/assets/img/img_1996.png",
        "/assets/img/img_1997.jpeg",
        "/assets/img/img_1998.png",
        "/assets/img/img_1999.jpg",
        "/assets/img/raining-road.jpg"
      ],
      "description": "Studying based on Goro-Fujita's style.  ",
      "icon": "/assets/img/pen-solid.svg",
      "link": {
        "text": "",
        "url": ""
      }
    },
    {
      "name": "Coming soon page",
      "description": "Neumorphism Design, Dark Mode, Countdown Timer",
      "icon": "/assets/img/desktop-solid.svg",
      "link": {
        "text": "Url",
        "url": "https://coming-soon-neumorphism.netlify.app/"
      },
      "thumnail": "/assets/img/capture.png"
    },
    {
      "name": "Not Found Page ver 1",
      "thumnail": "/assets/img/screen-shot-2020-09-17-at-14.28.38.png",
      "link": {
        "text": "404 page not found",
        "url": "https://404-notfound-flashlight.netlify.app/"
      },
      "description": "404 Page Not Found Demo Version 1"
    },
    {
      "name": "Branding Identity for \"Dai Nguyen Phu\" feng-shui shop",
      "thumnail": "/assets/img/1.png",
      "galleryImages": [
        "/assets/img/4.png",
        "/assets/img/5.png",
        "/assets/img/6.png",
        "/assets/img/7.png",
        "/assets/img/other.png"
      ],
      "link": {
        "text": "",
        "url": ""
      }
    }
  ]
}